LICENSE
MANIFEST.in
setup.py
Flask_SES.egg-info/PKG-INFO
Flask_SES.egg-info/SOURCES.txt
Flask_SES.egg-info/dependency_links.txt
Flask_SES.egg-info/not-zip-safe
Flask_SES.egg-info/requires.txt
Flask_SES.egg-info/top_level.txt
flask_ses/__init__.py