Metadata-Version: 1.1
Name: Flask-SES
Version: 0.1.1
Summary: Flask extension for interfacing with AWS' SES service
Home-page: https://github.com/stooie90/flask-ses
Author: Stuart Robertson
Author-email: stooie.robertson@gmail.com
License: MIT
Platform: any
Classifier: Environment :: Web Environment
Classifier: Intended Audience :: Developers
Classifier: License :: OSI Approved :: MIT License
Classifier: Operating System :: OS Independent
Classifier: Programming Language :: Python
Classifier: Topic :: Internet :: WWW/HTTP :: Dynamic Content
Classifier: Topic :: Software Development :: Libraries :: Python Modules
